cdk_skylight/__init__.py
cdk_skylight/py.typed
cdk_skylight/_jsii/__init__.py
cdk_skylight/_jsii/cdk-skylight@1.1.898.jsii.tgz
cdk_skylight/authentication/__init__.py
cdk_skylight/compute/__init__.py
cdk_skylight/storage/__init__.py
cdk_skylight-1.1.898.dist-info/LICENSE
cdk_skylight-1.1.898.dist-info/METADATA
cdk_skylight-1.1.898.dist-info/WHEEL
cdk_skylight-1.1.898.dist-info/top_level.txt
cdk_skylight-1.1.898.dist-info/RECORD
